{
  "url": "https://www.getclientell.com/roles-and-responsibilities",
  "title": "Roles and resposibilities of a Salesforce professional",
  "intent": "",
  "keywords": [],
  "internal_links": [
    "https://www.getclientell.com/roles-and-responsibilities/salesforce-marketing-cloud-specialist",
    "https://www.getclientell.com/roles-and-responsibilities/salesforce-business-analyst",
    "https://www.getclientell.com/roles-and-responsibilities/salesforce-architect",
    "https://www.getclientell.com/roles-and-responsibilities/salesforce-consultant",
    "https://www.getclientell.com/roles-and-responsibilities/salesforce-developer",
    "https://www.getclientell.com/roles-and-responsibilities/salesforce-admin",
    "https://www.getclientell.com/average-salary",
    "https://www.getclientell.com/cloud-services",
    "https://www.getclientell.com/",
    "https://www.getclientell.com/company/contact-us",
    "https://www.getclientell.com/company/contact-us",
    "https://www.getclientell.com/company/contact-us"
  ],
  "meta_description": "Roles and resposibilities of a Salesforce professional",
  "meta_keywords": [],
  "content": "Roles and Responsibilities of Salesforce JobsRoles and Responsibilities of Salesforce JobsExplore Salesforce job roles and responsibilities with ClientellRoles and Responsibilities of Salesforce Marketing Cloud SpecialistRoles and Responsibilities of Salesforce Marketing Cloud SpecialistRead moreRoles and Responsibilities of Salesforce Business AnalystRoles and Responsibilities of Salesforce Business AnalystRead moreRoles and Responsibilities of Salesforce ArchitectRoles and Responsibilities of Salesforce ArchitectRead moreRoles and Responsibilities of Salesforce ConsultantsRoles and Responsibilities of Salesforce ConsultantsRead moreRoles and Responsibilities of Salesforce DeveloperRoles and Responsibilities of Salesforce DeveloperRead moreRoles and Responsibilities of Salesforce AdminRoles and Responsibilities of Salesforce AdminRead moreSuggested ReadsSuggested ReadsWhat is the Average Salary for Salesforce Job RolesExplore moreExplore moreExplore moreSalesforce Cloud ImplementationExplore moreExplore moreExplore moreClientellYour ultimate RevOps and CRM dream teamYour ultimate RevOps and CRM dream teamYour ultimate RevOps and CRM dream teamContact UsContact UsContact UsConquer your GTM Tech Stack in 24 Hours",
  "pillar_keywords": [],
  "personas": [],
  "additional_keywords": [],
  "outline": [],
  "link_structure": {
    "internal": [
      "https://www.getclientell.com/roles-and-responsibilities/salesforce-marketing-cloud-specialist",
      "https://www.getclientell.com/roles-and-responsibilities/salesforce-business-analyst",
      "https://www.getclientell.com/roles-and-responsibilities/salesforce-architect",
      "https://www.getclientell.com/roles-and-responsibilities/salesforce-consultant",
      "https://www.getclientell.com/roles-and-responsibilities/salesforce-developer",
      "https://www.getclientell.com/roles-and-responsibilities/salesforce-admin",
      "https://www.getclientell.com/average-salary",
      "https://www.getclientell.com/cloud-services",
      "https://www.getclientell.com/",
      "https://www.getclientell.com/company/contact-us",
      "https://www.getclientell.com/company/contact-us",
      "https://www.getclientell.com/company/contact-us"
    ],
    "external": []
  },
  "timestamp": "2024-12-04 20:03:14"
}